.gitignore
Pipfile
README.md
setup.py
docs/Makefile
docs/make.bat
docs/source/conf.py
docs/source/index.rst
tiny_python_toolkit.egg-info/PKG-INFO
tiny_python_toolkit.egg-info/SOURCES.txt
tiny_python_toolkit.egg-info/dependency_links.txt
tiny_python_toolkit.egg-info/top_level.txt
tpt/__init__.py
tpt/visualize.py
tpt/tests/__init__.py
tpt/tests/test_visualize.py