Metadata-Version: 1.1
Name: tiny-python-toolkit
Version: 1.0.2
Summary: Collections of some useful tiny tool
Home-page: UNKNOWN
Author: UNKNOWN
Author-email: liyitingtom@gmail.com
License: UNKNOWN
Platform: UNKNOWN
Requires: typing
